rabbiteer/__init__.py
rabbiteer/client.py
rabbiteer-0.1.8.dist-info/METADATA
rabbiteer-0.1.8.dist-info/WHEEL
rabbiteer-0.1.8.dist-info/licenses/LICENSE
rabbiteer-0.1.8.dist-info/RECORD
