Metadata-Version: 2.4
Name: rabbiteer
Version: 0.1.8
Summary: A friendly and robust RabbitMQ client library for Python
Project-URL: Homepage, https://github.com/sebas-sala/rabbiteer
Project-URL: Bug Tracker, https://github.com/sebas-sala/rabbiteer/issues
Author-email: Sebastian Sala <sebastian.sala.alanis@hotmail.com>
License: MIT License
License-File: LICENSE
Classifier: License :: OSI Approved :: MIT License
Classifier: Operating System :: OS Independent
Classifier: Programming Language :: Python :: 3
Requires-Python: >=3.7
Requires-Dist: pika>=1.3.0
Requires-Dist: retry>=0.9.2
